{
  "psalm": 65,
  "verses": [
    {
      "v": 1,
      "text_he": "לַמְנַצֵּ֥חַ\n        מִזְמ֗וֹר\n        לְדָוִ֥ד\n        שִֽׁיר׃"
    },
    {
      "v": 2,
      "text_he": "לְךָ֤\n        דֻֽמִיָּ֬ה\n        תְהִלָּ֓ה\n        אֱלֹ֘הִ֥ים\n        בְּצִיּ֑וֹן\n        וּ֝לְךָ֗\n        יְשֻׁלַּם־\n        נֶֽדֶר׃"
    },
    {
      "v": 3,
      "text_he": "שֹׁמֵ֥עַ\n        תְּפִלָּ֑ה\n        עָ֝דֶ֗יךָ\n        כָּל־\n        בָּשָׂ֥ר\n        יָבֹֽאוּ׃"
    },
    {
      "v": 4,
      "text_he": "דִּבְרֵ֣י\n        עֲ֭וֺנֹת\n        גָּ֣בְרוּ\n        מֶ֑נִּי\n        פְּ֝שָׁעֵ֗ינוּ\n        אַתָּ֥ה\n        תְכַפְּרֵֽם׃"
    },
    {
      "v": 5,
      "text_he": "אַשְׁרֵ֤י ׀\n        תִּֽבְחַ֣ר\n        וּתְקָרֵב֮\n        יִשְׁכֹּ֢ן\n        חֲצֵ֫רֶ֥יךָ\n        נִ֭שְׂבְּעָה\n        בְּט֣וּב\n        בֵּיתֶ֑ךָ\n        קְ֝דֹ֗שׁ\n        הֵיכָלֶֽךָ׃"
    },
    {
      "v": 6,
      "text_he": "נ֤וֹרָא֨וֹת ׀\n        בְּצֶ֣דֶק\n        תַּ֭עֲנֵנוּ\n        אֱלֹהֵ֣י\n        יִשְׁעֵ֑נוּ\n        מִבְטָ֥ח\n        כָּל־\n        קַצְוֵי־\n        אֶ֝֗רֶץ\n        וְיָ֣ם\n        רְחֹקִֽים׃"
    },
    {
      "v": 7,
      "text_he": "מֵכִ֣ין\n        הָרִ֣ים\n        בְּכֹח֑וֹ\n        נֶ֝אְזָ֗ר\n        בִּגְבוּרָֽה׃"
    },
    {
      "v": 8,
      "text_he": "מַשְׁבִּ֤יחַ ׀\n        שְׁא֣וֹן\n        יַ֭מִּים\n        שְׁא֥וֹן\n        גַּלֵּיהֶ֗ם\n        וַהֲמ֥וֹן\n        לְאֻמִּֽים׃"
    },
    {
      "v": 9,
      "text_he": "וַיִּ֤ירְא֨וּ ׀\n        יֹשְׁבֵ֣י\n        קְ֭צָוֺת\n        מֵאוֹתֹתֶ֑יךָ\n        מ֤וֹצָֽאֵי־\n        בֹ֖קֶר\n        וָעֶ֣רֶב\n        תַּרְנִֽין׃"
    },
    {
      "v": 10,
      "text_he": "פָּ֤קַֽדְתָּ\n        הָאָ֨רֶץ ׀\n        וַתְּשֹׁ֪קְקֶ֡הָ\n        רַבַּ֬ת\n        תַּעְשְׁרֶ֗נָּה\n        פֶּ֣לֶג\n        אֱ֭לֹהִים\n        מָ֣לֵא\n        מָ֑יִם\n        תָּכִ֥ין\n        דְּ֝גָנָ֗ם\n        כִּי־\n        כֵ֥ן\n        תְּכִינֶֽהָ׃"
    },
    {
      "v": 11,
      "text_he": "תְּלָמֶ֣יהָ\n        רַ֭וֵּה\n        נַחֵ֣ת\n        גְּדוּדֶ֑יהָ\n        בִּרְבִיבִ֥ים\n        תְּ֝מֹגְגֶ֗נָּה\n        צִמְחָ֥הּ\n        תְּבָרֵֽךְ׃"
    },
    {
      "v": 12,
      "text_he": "עִ֭טַּרְתָּ\n        שְׁנַ֣ת\n        טוֹבָתֶ֑ךָ\n        וּ֝מַעְגָּלֶ֗יךָ\n        יִרְעֲפ֥וּן\n        דָּֽשֶׁן׃"
    },
    {
      "v": 13,
      "text_he": "יִ֭רְעֲפוּ\n        נְא֣וֹת\n        מִדְבָּ֑ר\n        וְ֝גִ֗יל\n        גְּבָע֥וֹת\n        תַּחְגֹּֽרְנָה׃"
    },
    {
      "v": 14,
      "text_he": "לָבְשׁ֬וּ\n        כָרִ֨ים ׀\n        הַצֹּ֗אן\n        וַעֲמָקִ֥ים\n        יַֽעַטְפוּ־\n        בָ֑ר\n        יִ֝תְרוֹעֲע֗וּ\n        אַף־\n        יָשִֽׁירוּ׃"
    }
  ],
  "stats": {
    "verses": 14,
    "chars_no_diacritics": 586,
    "words": 115
  }
}