{
  "psalm": 73,
  "verses": [
    {
      "v": 1,
      "text_he": "מִזְמ֗וֹר\n        לְאָ֫סָ֥ף\n        אַ֤ךְ\n        ט֖וֹב\n        לְיִשְׂרָאֵ֥ל\n        אֱלֹהִ֗ים\n        לְבָרֵ֥י\n        לֵבָֽב׃"
    },
    {
      "v": 2,
      "text_he": "וַאֲנִ֗י\n        כִּ֭מְעַט\n        נטוי\n        נָטָ֣יוּ\n        רַגְלָ֑י\n        כְּ֝אַ֗יִן\n        שפכה\n        שֻׁפְּכ֥וּ\n        אֲשֻׁרָֽי׃"
    },
    {
      "v": 3,
      "text_he": "כִּֽי־\n        קִ֭נֵּאתִי\n        בַּֽהוֹלְלִ֑ים\n        שְׁל֖וֹם\n        רְשָׁעִ֣ים\n        אֶרְאֶֽה׃"
    },
    {
      "v": 4,
      "text_he": "כִּ֤י\n        אֵ֖ין\n        חַרְצֻבּ֥וֹת\n        לְמוֹתָ֗ם\n        וּבָרִ֥יא\n        אוּלָֽם׃"
    },
    {
      "v": 5,
      "text_he": "בַּעֲמַ֣ל\n        אֱנ֣וֹשׁ\n        אֵינֵ֑מוֹ\n        וְעִם־\n        אָ֝דָ֗ם\n        לֹ֣א\n        יְנֻגָּֽעוּ׃"
    },
    {
      "v": 6,
      "text_he": "לָ֭כֵן\n        עֲנָקַ֣תְמוֹ\n        גַאֲוָ֑ה\n        יַעֲטָף־\n        שִׁ֝֗ית\n        חָמָ֥ס\n        לָֽמוֹ׃"
    },
    {
      "v": 7,
      "text_he": "יָ֭צָא\n        מֵחֵ֣לֶב\n        עֵינֵ֑מוֹ\n        עָ֝בְר֗וּ\n        מַשְׂכִּיּ֥וֹת\n        לֵבָֽב׃"
    },
    {
      "v": 8,
      "text_he": "יָמִ֤יקוּ ׀\n        וִידַבְּר֣וּ\n        בְרָ֣ע\n        עֹ֑שֶׁק\n        מִמָּר֥וֹם\n        יְדַבֵּֽרוּ׃"
    },
    {
      "v": 9,
      "text_he": "שַׁתּ֣וּ\n        בַשָּׁמַ֣יִם\n        פִּיהֶ֑ם\n        וּ֝לְשׁוֹנָ֗ם\n        תִּֽהֲלַ֥ךְ\n        בָּאָֽרֶץ׃"
    },
    {
      "v": 10,
      "text_he": "לָכֵ֤ן ׀\n        ישיב\n        יָשׁ֣וּב\n        עַמּ֣וֹ\n        הֲלֹ֑ם\n        וּמֵ֥י\n        מָ֝לֵ֗א\n        יִמָּ֥צוּ\n        לָֽמוֹ׃"
    },
    {
      "v": 11,
      "text_he": "וְֽאָמְר֗וּ\n        אֵיכָ֥ה\n        יָדַֽע־\n        אֵ֑ל\n        וְיֵ֖שׁ\n        דֵּעָ֣ה\n        בְעֶלְיֽוֹן׃"
    },
    {
      "v": 12,
      "text_he": "הִנֵּה־\n        אֵ֥לֶּה\n        רְשָׁעִ֑ים\n        וְשַׁלְוֵ֥י\n        ע֝וֹלָ֗ם\n        הִשְׂגּוּ־\n        חָֽיִל׃"
    },
    {
      "v": 13,
      "text_he": "אַךְ־\n        רִ֭יק\n        זִכִּ֣יתִי\n        לְבָבִ֑י\n        וָאֶרְחַ֖ץ\n        בְּנִקָּי֣וֹן\n        כַּפָּֽי׃"
    },
    {
      "v": 14,
      "text_he": "וָאֱהִ֣י\n        נָ֭גוּעַ\n        כָּל־\n        הַיּ֑וֹם\n        וְ֝תוֹכַחְתִּ֗י\n        לַבְּקָרִֽים׃"
    },
    {
      "v": 15,
      "text_he": "אִם־\n        אָ֭מַרְתִּי\n        אֲסַפְּרָ֥ה\n        כְמ֑וֹ\n        הִנֵּ֤ה\n        ד֭וֹר\n        בָּנֶ֣יךָ\n        בָגָֽדְתִּי׃"
    },
    {
      "v": 16,
      "text_he": "וָֽ֭אֲחַשְּׁבָה\n        לָדַ֣עַת\n        זֹ֑את\n        עָמָ֖ל\n        היא\n        ה֣וּא\n        בְעֵינָֽי׃"
    },
    {
      "v": 17,
      "text_he": "עַד־\n        אָ֭בוֹא\n        אֶל־\n        מִקְדְּשֵׁי־\n        אֵ֑ל\n        אָ֝בִ֗ינָה\n        לְאַחֲרִיתָֽם׃"
    },
    {
      "v": 18,
      "text_he": "אַ֣ךְ\n        בַּ֭חֲלָקוֹת\n        תָּשִׁ֣ית\n        לָ֑מוֹ\n        הִ֝פַּלְתָּ֗ם\n        לְמַשּׁוּאֽוֹת׃"
    },
    {
      "v": 19,
      "text_he": "אֵ֤יךְ\n        הָי֣וּ\n        לְשַׁמָּ֣ה\n        כְרָ֑גַע\n        סָ֥פוּ\n        תַ֝֗מּוּ\n        מִן־\n        בַּלָּהֽוֹת׃"
    },
    {
      "v": 20,
      "text_he": "כַּחֲל֥וֹם\n        מֵהָקִ֑יץ\n        אֲ֝דֹנָי\n        בָּעִ֤יר ׀\n        צַלְמָ֬ם\n        תִּבְזֶֽה׃"
    },
    {
      "v": 21,
      "text_he": "כִּ֭י\n        יִתְחַמֵּ֣ץ\n        לְבָבִ֑י\n        וְ֝כִלְיוֹתַ֗י\n        אֶשְׁתּוֹנָֽן׃"
    },
    {
      "v": 22,
      "text_he": "וַאֲנִי־\n        בַ֭עַר\n        וְלֹ֣א\n        אֵדָ֑ע\n        בְּ֝הֵמ֗וֹת\n        הָיִ֥יתִי\n        עִמָּֽךְ׃"
    },
    {
      "v": 23,
      "text_he": "וַאֲנִ֣י\n        תָמִ֣יד\n        עִמָּ֑ךְ\n        אָ֝חַ֗זְתָּ\n        בְּיַד־\n        יְמִינִֽי׃"
    },
    {
      "v": 24,
      "text_he": "בַּעֲצָתְךָ֥\n        תַנְחֵ֑נִי\n        וְ֝אַחַ֗ר\n        כָּב֥וֹד\n        תִּקָּחֵֽנִי׃"
    },
    {
      "v": 25,
      "text_he": "מִי־\n        לִ֥י\n        בַשָּׁמָ֑יִם\n        וְ֝עִמְּךָ֗\n        לֹא־\n        חָפַ֥צְתִּי\n        בָאָֽרֶץ׃"
    },
    {
      "v": 26,
      "text_he": "כָּלָ֥ה\n        שְׁאֵרִ֗י\n        וּלְבָ֫בִ֥י\n        צוּר־\n        לְבָבִ֥י\n        וְחֶלְקִ֗י\n        אֱלֹהִ֥ים\n        לְעוֹלָֽם׃"
    },
    {
      "v": 27,
      "text_he": "כִּֽי־\n        הִנֵּ֣ה\n        רְחֵקֶ֣יךָ\n        יֹאבֵ֑דוּ\n        הִ֝צְמַ֗תָּה\n        כָּל־\n        זוֹנֶ֥ה\n        מִמֶּֽךָּ׃"
    },
    {
      "v": 28,
      "text_he": "וַאֲנִ֤י ׀\n        קִֽרֲבַ֥ת\n        אֱלֹהִ֗ים\n        לִ֫י־\n        ט֥וֹב\n        שַׁתִּ֤י ׀\n        בַּאדֹנָ֣י\n        יְהֹוִ֣ה\n        מַחְסִ֑י\n        לְ֝סַפֵּ֗ר\n        כָּל־\n        מַלְאֲכוֹתֶֽיךָ׃"
    }
  ],
  "stats": {
    "verses": 28,
    "chars_no_diacritics": 1007,
    "words": 202
  }
}